idem_aix/conf.py
idem_aix/version.py
idem_aix/exec/aix/init.py
idem_aix/grains/aix/defaults.py
idem_aix/grains/aix/init.py
idem_aix/grains/aix/hw/bios.py
idem_aix/grains/aix/hw/cpu.py
idem_aix/grains/aix/hw/disks.py
idem_aix/grains/aix/hw/gpu.py
idem_aix/grains/aix/hw/iscsi.py
idem_aix/grains/aix/hw/mem.py
idem_aix/grains/aix/net/gateway.py
idem_aix/grains/aix/net/interfaces.py
idem_aix/grains/aix/os/os.py
idem_aix/states/aix/init.py
idem_aix-4.2.dist-info/METADATA
idem_aix-4.2.dist-info/WHEEL
idem_aix-4.2.dist-info/top_level.txt
idem_aix-4.2.dist-info/RECORD
