Metadata-Version: 2.1
Name: idem-aix
Version: 4.2
Summary: Vertical app merge components for Idem and grains support on AIX
Home-page: https://gitlab.com/saltstack/pop/idem-aix
Author: Tyler Johnson
Author-email: tjohnson@saltstack.com
License: UNKNOWN
Platform: UNKNOWN
Classifier: Operating System :: POSIX :: AIX
Classifier: Programming Language :: Python
Classifier: Programming Language :: Python :: 3.6
Classifier: Programming Language :: Python :: 3.7
Classifier: Programming Language :: Python :: 3.8
Classifier: Development Status :: 5 - Production/Stable
Requires-Python: >=3.6
Requires-Dist: idem-posix (>=2.1)
